{
  "users": [
    {
      "id": 1,
      "firstname": "Nickie",
      "lastname": "Brieta",
      "city": "Petropavlovsk-Kamchatsky",
      "country": "Bermuda",
      "email": "Nickie.Brieta@gmail.com"
    },
    {
      "id": 2,
      "firstname": "Anica",
      "lastname": "Thomasina",
      "city": "Surat",
      "country": "Central African Republic",
      "email": "Anica.Thomasina@gmail.com"
    },
    {
      "id": 3,
      "firstname": "Suzette",
      "lastname": "Alva",
      "city": "Zürich",
      "country": "Lao People\"S Democratic Republic",
      "email": "Suzette.Alva@gmail.com"
    },
    {
      "id": 4,
      "firstname": "Ulrike",
      "lastname": "Capello",
      "city": "Vitória",
      "country": "Bermuda",
      "email": "Ulrike.Capello@gmail.com"
    },
    {
      "id": 5,
      "firstname": "Frank",
      "lastname": "Wattenberg",
      "city": "Mamoudzou",
      "country": "Lebanon",
      "email": "Frank.Wattenberg@gmail.com"
    },
    {
      "id": 6,
      "firstname": "Agnese",
      "lastname": "Georas",
      "city": "Milwaukee",
      "country": "Jersey",
      "email": "Agnese.Georas@gmail.com"
    },
    {
      "firstname": "sss",
      "lastname": "asdada",
      "email": "kadryokkd@ukr.net",
      "country": "sddsD",
      "city": "SAdsD",
      "id": 100
    },
    {
      "firstname": "Andrii",
      "lastname": "Sovtus",
      "email": "kadryokkd@ukr.net",
      "country": "Ukraine",
      "city": "Ivano-Frankivsk",
      "id": "Wed Nov 30 2022 19:05:08 GMT+0200 (за східноєвропейським стандартним часом)"
    },
    {
      "firstname": "Andrii",
      "lastname": "Perchyn",
      "email": "kadryokkd@ukr.net",
      "country": "Ukraine",
      "city": "Ivano-Frankivsk",
      "id": "Wed Nov 30 2022 19:06:07 GMT+0200 (за східноєвропейським стандартним часом)"
    },
    {
      "firstname": "Andrii",
      "lastname": "BBB",
      "email": "kadryokkd@ukr.net",
      "country": "Ssadasd",
      "city": "asdasda",
      "id": "Wed Nov 30 2022 19:18:01 GMT+0200 (за східноєвропейським стандартним часом)"
    },
    {
      "firstname": "Test",
      "lastname": "Test",
      "email": "kadryokkd@ukr.net",
      "country": "Test",
      "city": "asdasda",
      "id": "Wed Nov 30 2022 19:53:29 GMT+0200 (за східноєвропейським стандартним часом)"
    },
    {
      "firstname": "Test",
      "lastname": "Test",
      "email": "kadryokkd@ukr.net",
      "country": "Test",
      "city": "asdasda",
      "id": "Wed Nov 30 2022 19:53:34 GMT+0200 (за східноєвропейським стандартним часом)"
    },
    {
      "firstname": "Test",
      "lastname": "Test",
      "email": "kadryokkd@ukr.net",
      "country": "Test",
      "city": "asdasda",
      "id": "Wed Nov 30 2022 19:55:56 GMT+0200 (за східноєвропейським стандартним часом)"
    },
    {
      "firstname": "Andrii",
      "lastname": "Sovtus",
      "email": "samsuser570@gmail.com",
      "country": "Україна",
      "city": "ivano-frankivsk",
      "id": "Wed Nov 30 2022 21:08:35 GMT+0200 (за східноєвропейським стандартним часом)"
    },
    {
      "firstname": "Andrii",
      "lastname": "Sovtus",
      "email": "andrii.sovtus.21@pnu.edu.ua",
      "country": "Україна",
      "city": "ivano-frankivsk",
      "id": "Thu Dec 01 2022 10:49:27 GMT+0200 (за східноєвропейським стандартним часом)"
    },
    {
      "firstname": "Andrii",
      "lastname": "Sovtus",
      "email": "samsuser570@gmail.com",
      "country": "Україна",
      "city": "ivano-frankivsk",
      "id": "Thu Dec 01 2022 10:49:40 GMT+0200 (за східноєвропейським стандартним часом)"
    },
    {
      "firstname": "Andrii",
      "lastname": "Sovtus",
      "email": "andrii.sovtus.21@pnu.edu.ua",
      "country": "Україна",
      "city": "ivano-frankivsk",
      "id": "Thu Dec 01 2022 10:49:45 GMT+0200 (за східноєвропейським стандартним часом)"
    },
    {
      "firstname": "Andrii",
      "lastname": "Sovtus",
      "email": "andrii2004s@gmail.com",
      "country": "Україна",
      "city": "ivano-frankivsk",
      "id": "Thu Dec 01 2022 11:11:24 GMT+0200 (за східноєвропейським стандартним часом)"
    },
    {
      "firstname": "Andrii",
      "lastname": "Sovtus",
      "email": "andrii2004s@gmail.com",
      "country": "Україна",
      "city": "ivano-frankivsk",
      "id": "Thu Dec 01 2022 11:12:33 GMT+0200 (за східноєвропейським стандартним часом)"
    },
    {
      "firstname": "Andrii",
      "lastname": "Sovtus",
      "email": "andrii2004s@gmail.com",
      "country": "Україна",
      "city": "ivano-frankivsk",
      "id": "Thu Dec 01 2022 11:12:39 GMT+0200 (за східноєвропейським стандартним часом)"
    },
    {
      "firstname": "Andrii",
      "lastname": "Sovtus",
      "email": "samsuser570@gmail.com",
      "country": "Україна",
      "city": "ivano-frankivsk",
      "id": "Thu Dec 01 2022 11:14:56 GMT+0200 (за східноєвропейським стандартним часом)"
    },
    {
      "firstname": "Andrii",
      "lastname": "Sovtus",
      "email": "samsuser570@gmail.com",
      "country": "Україна",
      "city": "ivano-frankivsk",
      "id": "Thu Dec 01 2022 11:17:30 GMT+0200 (за східноєвропейським стандартним часом)"
    },
    {
      "firstname": "Andrii",
      "lastname": "Sovtus",
      "email": "samsuser570@gmail.com",
      "country": "Україна",
      "city": "ivano-frankivsk",
      "id": "Thu Dec 01 2022 11:21:46 GMT+0200 (за східноєвропейським стандартним часом)"
    },
    {
      "firstname": "Andrii",
      "lastname": "Sovtus",
      "email": "andrii.sovtus.21@pnu.edu.ua",
      "country": "Україна",
      "city": "ivano-frankivsk",
      "id": "Thu Dec 01 2022 11:21:52 GMT+0200 (за східноєвропейським стандартним часом)"
    },
    {
      "firstname": "Andrii",
      "lastname": "Sovtus",
      "email": "samsuser570@gmail.com",
      "country": "Україна",
      "city": "ivano-frankivsk",
      "id": "Thu Dec 01 2022 11:22:54 GMT+0200 (за східноєвропейським стандартним часом)"
    },
    {
      "firstname": "Andrii",
      "lastname": "Sovtus",
      "email": "samsuser570@gmail.com",
      "country": "Україна",
      "city": "ivano-frankivsk",
      "id": "Thu Dec 01 2022 11:23:26 GMT+0200 (за східноєвропейським стандартним часом)"
    },
    {
      "firstname": "Andrii",
      "lastname": "Sovtus",
      "email": "andrii2004s@gmail.com",
      "country": "Україна",
      "city": "ivano-frankivsk",
      "id": "Thu Dec 01 2022 11:23:32 GMT+0200 (за східноєвропейським стандартним часом)"
    },
    {
      "firstname": "Andrii",
      "lastname": "Sovtus",
      "email": "samsuser570@gmail.com",
      "country": "Україна",
      "city": "ivano-frankivsk",
      "id": "Thu Dec 01 2022 11:23:38 GMT+0200 (за східноєвропейським стандартним часом)"
    },
    {
      "firstname": "Andrii",
      "lastname": "Sovtus",
      "email": "andrii2004s@gmail.com",
      "country": "Україна",
      "city": "ivano-frankivsk",
      "id": "Thu Dec 01 2022 11:23:46 GMT+0200 (за східноєвропейським стандартним часом)"
    },
    {
      "firstname": "Andrii",
      "lastname": "Sovtus",
      "email": "andrii2004s@gmail.com",
      "country": "Україна",
      "city": "ivano-frankivsk",
      "id": "Thu Dec 01 2022 11:26:38 GMT+0200 (за східноєвропейським стандартним часом)"
    },
    {
      "firstname": "Andrii",
      "lastname": "Sovtus",
      "email": "samsuser570@gmail.com",
      "country": "Україна",
      "city": "ivano-frankivsk",
      "id": "Thu Dec 01 2022 11:40:44 GMT+0200 (за східноєвропейським стандартним часом)"
    }
  ],
  "headers": [
    "firstname",
    "lastname",
    "email",
    "country",
    "city"
  ]
}